pydantic2sqlalchemytk/__init__.py
pydantic2sqlalchemytk/lib.py
pydantic2sqlalchemytk/run.py
pydantic2sqlalchemytk-1.0.0.dist-info/WHEEL
pydantic2sqlalchemytk-1.0.0.dist-info/METADATA
pydantic2sqlalchemytk-1.0.0.dist-info/RECORD
